CSLab #1/8Adder.v
`ifndef _8ADDER_V
`define _8ADDER_V

`include "fAdder.v"

module Adder8(
    input [7:0] A, B,
    input Cin,
    output [7:0] Sum,
    output Cout    
);
    wire [7:1] Ctemp;
    Full_Adder F0(A[0], B[0], Cin, Sum[0], Ctemp[1]);
    Full_Adder F1(A[1], B[1], Ctemp[1], Sum[1], Ctemp[2]);
    Full_Adder F2(A[2], B[2], Ctemp[2], Sum[2], Ctemp[3]);
    Full_Adder F3(A[3], B[3], Ctemp[3], Sum[3], Ctemp[4]);
    Full_Adder F4(A[4], B[4], Ctemp[4], Sum[4], Ctemp[5]);
    Full_Adder F5(A[5], B[5], Ctemp[5], Sum[5], Ctemp[6]);
    Full_Adder F6(A[6], B[6], Ctemp[6], Sum[6], Ctemp[7]);
    Full_Adder F7(A[7], B[7], Ctemp[7], Sum[7], Cout);
endmodule

`endif

CSLab #1/fAdder.v
`ifndef _FADDER_V
`define _FADDER_V

module Full_Adder(
    input A, B, Cin,
    output Sum, Cout    
);
    // assign Sum = A ^ B ^ Cin;
    // assign Cout = (A & B) | (A & Cin) | (B & Cin);
    assign {Cout, Sum} = A + B + Cin;
endmodule

`endif

CSLab #1/nAdder.v
`ifndef _NADDER_V
`define _NADDER_V

`include "fAdder.v"

module nAdder #(parameter N = 8) (
    input [N-1 : 0] A, B,
    input Cin,
    output [N-1 : 0] Sum,
    output Cout
);  
    wire [N : 0] Ctemp;

    assign Ctemp[0] = Cin;
    generate
        for (genvar i=0; i<N; i=i+1) 
            Full_Adder f_i(A[i], B[i], Ctemp[i], Sum[i], Ctemp[i+1]);
    endgenerate
    assign Cout = Ctemp[N];

endmodule

`endif

CSLab #1/nAdder_tb.v
`include "8Adder.v"
`include "nAdder.v"

module nAdder_tb;

    reg [7:0] A, B;
    reg C;
    wire [7:0] S;
    wire Cout;
    
    // Adder8  F(A, B, C, S, Cout);
    nAdder #(8)  F1(A, B, C, S, Cout);

    initial begin
        $dumpfile("nAdder.vcd");
        $dumpvars(1, nAdder_tb);
        
        $monitor("Time: %3g\tA: %4d\tB: %4d\tCin: %b\tCout: %b\tSum: %4d", $time, A, B, C, Cout, S);

        #5 A=8'd0; B=8'd250; C=1'b0;
        #5 A=8'd1; B=8'd250; C=1'b0;
        #5 A=8'd2; B=8'd250; C=1'b0;
        #5 A=8'd3; B=8'd250; C=1'b0;
        #5 A=8'd4; B=8'd250; C=1'b0;
        #5 A=8'd5; B=8'd250; C=1'b0;
        #5 A=8'd6; B=8'd250; C=1'b0;
        #5 A=8'd7; B=8'd250; C=1'b0;
        #5 A=8'd8; B=8'd250; C=1'b0;
        #5 A=8'd9; B=8'd250; C=1'b0;
        #5 A=8'd0; B=8'd250; C=1'b1;
        #5 A=8'd1; B=8'd250; C=1'b1;
        #5 A=8'd2; B=8'd250; C=1'b1;
        #5 A=8'd3; B=8'd250; C=1'b1;
        #5 A=8'd4; B=8'd250; C=1'b1;
        #5 A=8'd5; B=8'd250; C=1'b1;
        #5 A=8'd6; B=8'd250; C=1'b1;
        #5 A=8'd7; B=8'd250; C=1'b1;
        #5 A=8'd8; B=8'd250; C=1'b1;
        #5 A=8'd9; B=8'd250; C=1'b1;
        #5 $finish;
    end

endmodule

CSLab #1/nAdder.vcd
$date
	Wed Oct 11 15:18:35 2023
$end
$version
	Icarus Verilog
$end
$timescale
	1s
$end
$scope module nAdder_tb $end
$var wire 8 ! S [7:0] $end
$var wire 1 " Cout $end
$var reg 8 # A [7:0] $end
$var reg 8 $ B [7:0] $end
$var reg 1 % C $end
$upscope $end
$enddefinitions $end
#0
$dumpvars
x%
bx $
bx #
x"
bx !
$end
#5
0"
b11111010 !
0%
b11111010 $
b0 #
#10
b11111011 !
b1 #
#15
b11111100 !
b10 #
#20
b11111101 !
b11 #
#25
0"
b11111110 !
b100 #
#30
b11111111 !
b101 #
#35
1"
b0 !
b110 #
#40
b1 !
b111 #
#45
b10 !
b1000 #
#50
b11 !
b1001 #
#55
0"
b11111011 !
1%
b0 #
#60
b11111100 !
b1 #
#65
b11111101 !
b10 #
#70
b11111110 !
b11 #
#75
0"
b11111111 !
b100 #
#80
1"
b0 !
b101 #
#85
b1 !
b110 #
#90
b10 !
b111 #
#95
b11 !
b1000 #
#100
b100 !
b1001 #
