CSLab #2/src/FAdder.v
`ifndef _FULL_ADDER
`define _FULL_ADDER

module Full_Adder (
    output Cout, Sum,
    input A, B, Cin
);
    assign Cout = (A & B) | (B & Cin) | (A & Cin);
    assign Sum = A ^ B ^ Cin;
endmodule

`endif

CSLab #2/Adder8.v
`ifndef _8_BITS_ADDER
`define _8_BITS_ADDER

`include "FAdder.v"

module Adder8 (
    output Cout, 
    output [7:0] Sum,
    input [7:0] A, B,
    input Cin
);
    // always @(*) begin
    //     $monitor("**time: %02g, A: %08b, B: %08b, S: %08b", $time, A, B, Sum);
    // end
    wire [7:1] ctemp;
    Full_Adder F0(ctemp[1], Sum[0], A[0], B[0], Cin);
    Full_Adder F1(ctemp[2], Sum[1], A[1], B[1], ctemp[1]);
    Full_Adder F2(ctemp[3], Sum[2], A[2], B[2], ctemp[2]);
    Full_Adder F3(ctemp[4], Sum[3], A[3], B[3], ctemp[3]);
    Full_Adder F4(ctemp[5], Sum[4], A[4], B[4], ctemp[4]);
    Full_Adder F5(ctemp[6], Sum[5], A[5], B[5], ctemp[5]);
    Full_Adder F6(ctemp[7], Sum[6], A[6], B[6], ctemp[6]);
    Full_Adder F7(Cout,     Sum[7], A[7], B[7], ctemp[7]);
endmodule

`endif

CSLab #2/FSM.v
`ifndef _FINITE_STATE_MACHINE 
`define _FINITE_STATE_MACHINE

module MUL_FSM (
    output reg [1:0] state,
    input clk, areset, 
    input [7:0] multiplier
);
    parameter INIT = 0;
    parameter EXEC = 1;
    parameter IDLE = 2;
    parameter HALT = 3;

    reg [3:0] counter;

    always @(posedge clk, areset) begin
        $monitor("[%2g] arst: %b, counter: %d, next_state: %d", $time, areset, counter, state);
        if (areset) begin
            state = INIT;
            counter = 0;
        end
        else if (counter >= 8) begin
            state = HALT;
        end
        else if (multiplier[0]) begin
            state = EXEC;
            counter = counter + 1;
        end
        else if (~multiplier[0])  begin
            state = IDLE;
            counter = counter + 1;
        end
        else begin // multiplier[0] == x
            state = INIT;
            counter = 0;
            $display("[%2g] multiplier[0] == x", $time);
        end
    end
endmodule
`endif

CSLab #2/Multiplier_modules.v
`ifndef _8x8_MULTIPLIER
`define _8x8_MULTIPLIER

`include "Adder8.v"
`include "FSM.v"

// performing out = A * B
module multiplier8x8 (
    output reg [15:0] product,
    input [7:0] multiplicand, multiplier,
    input clk, areset
);
    parameter INIT = 0;
    parameter EXEC = 1;
    parameter IDLE = 2;
    parameter HALT = 3;

    reg [7:0] B;
    wire [7:0] tempSum; 
    wire Cout;
    reg [1:0] state; 
    wire [1:0] next_state;

    MUL_FSM ControlUnit(
        .state(next_state),
        .multiplier(B),
        .clk(clk),
        .areset(areset)
    );

    Adder8 ALU(
        .Cout(Cout), 
        .Sum(tempSum),
        .A(product[15:8]), 
        .B(multiplicand),
        .Cin(1'b0)
    );
    
    always @(negedge clk) $display("");

    // state transition logic
    always @(posedge clk) begin 
        $display("[%2g] B: %08b , state: %d", $time, B, state);
        // if (areset) begin
        //     B = multiplier;
        //     product = 16'b0;
        // end
        if (state == HALT && areset) begin
            B = multiplier;
            product = 16'b0;
        end
        else if (state == INIT) begin
            B = multiplier;
            product = 16'b0;
        end
        else if (state == EXEC) begin
            $display("[%2g] EXEC: prod: %8b, tempSum: %08b", $time, product[7:1], tempSum);
            product = {Cout, tempSum, product[7:1]};
            B = {1'b0, B[7:1]};
            $display("[%2g] product: %08b %08b | %8d", $time, product[15:8], product[7:0], product);
        end
        else if (state == IDLE) begin
            product = {1'b0, product[15:1]};
            B = {1'b0, B[7:1]};
            $display("[%2g] product: %08b %08b | %8d", $time, product[15:8], product[7:0], product);
        end
        else begin // HALT
            product = product;
            B = B;
            $display("[%2g] product: %08b %08b | %8d", $time, product[15:8], product[7:0], product);
        end
    end

    always @(negedge clk) state = next_state;

endmodule
`endif

CSLab #2/mul_s_tb.v
`include "Multiplier_modules.v"

module tb;
    reg [7:0] A, B;
    reg clk, areset;
    wire [15:0] product;

    multiplier8x8 M(product, A, B, clk, areset);

    initial begin
        $dumpfile("mul.vcd");
        $dumpvars(0, tb);

        clk = 0;
        #5 areset = 1; A = 8'd255; B = 8'd100; clk = 1; 
        #5 clk = 0; areset = 0; clk = 1;
        #5 clk = 0; clk = 1;
        #5 clk = 0; clk = 1;
        #5 clk = 0; clk = 1;
        #5 clk = 0; clk = 1;
        #5 clk = 0; clk = 1;
        #5 clk = 0; clk = 1;
        #5 clk = 0; clk = 1;
        #5 clk = 0; clk = 1;
        #5 clk = 0; clk = 1;
        #5 clk = 0; clk = 1;
        #5 clk = 0; clk = 1;

        $display("\n-----\n");
                
        #5 clk = 0; areset = 1; A = 8'd255; B = 8'd255; clk = 1; 
        #5 clk = 0; areset = 0; clk = 1;
        #5 clk = 0; clk = 1;
        #5 clk = 0; clk = 1;
        #5 clk = 0; clk = 1;
        #5 clk = 0; clk = 1;
        #5 clk = 0; clk = 1;
        #5 clk = 0; clk = 1;
        #5 clk = 0; clk = 1;
        #5 clk = 0; clk = 1;
        #5 clk = 0; clk = 1;
        #5 clk = 0; clk = 1;
        #5 clk = 0; clk = 1;

        $display("\n-----\n");
                
        #5 clk = 0; areset = 1; A = 8'd1; B = 8'd1; clk = 1; 
        #5 clk = 0; areset = 0; clk = 1;
        #5 clk = 0; clk = 1;
        #5 clk = 0; clk = 1;
        #5 clk = 0; clk = 1;
        #5 clk = 0; clk = 1;
        #5 clk = 0; clk = 1;
        #5 clk = 0; clk = 1;
        #5 clk = 0; clk = 1;
        #5 clk = 0; clk = 1;
        #5 clk = 0; clk = 1;
        #5 clk = 0; clk = 1;
        #5 clk = 0; clk = 1;
    end

endmodule

CSLab #2/mul.vcd
$date
	Thu Oct 12 16:41:03 2023
$end
$version
	Icarus Verilog
$end
$timescale
	1s
$end
$scope module tb $end
$var wire 16 ! product [15:0] $end
$var reg 8 " A [7:0] $end
$var reg 8 # B [7:0] $end
$var reg 1 $ areset $end
$var reg 1 % clk $end
$scope module M $end
$var wire 1 $ areset $end
$var wire 1 % clk $end
$var wire 8 & multiplicand [7:0] $end
$var wire 8 ' multiplier [7:0] $end
$var wire 8 ( tempSum [7:0] $end
$var wire 2 ) next_state [1:0] $end
$var wire 1 * Cout $end
$var reg 8 + B [7:0] $end
$var reg 16 , product [15:0] $end
$var reg 2 - state [1:0] $end
$scope module ALU $end
$var wire 8 . A [7:0] $end
$var wire 8 / B [7:0] $end
$var wire 1 0 Cin $end
$var wire 7 1 ctemp [7:1] $end
$var wire 8 2 Sum [7:0] $end
$var wire 1 * Cout $end
$scope module F0 $end
$var wire 1 3 A $end
$var wire 1 4 B $end
$var wire 1 0 Cin $end
$var wire 1 5 Cout $end
$var wire 1 6 Sum $end
$upscope $end
$scope module F1 $end
$var wire 1 7 A $end
$var wire 1 8 B $end
$var wire 1 9 Cin $end
$var wire 1 : Cout $end
$var wire 1 ; Sum $end
$upscope $end
$scope module F2 $end
$var wire 1 < A $end
$var wire 1 = B $end
$var wire 1 > Cin $end
$var wire 1 ? Cout $end
$var wire 1 @ Sum $end
$upscope $end
$scope module F3 $end
$var wire 1 A A $end
$var wire 1 B B $end
$var wire 1 C Cin $end
$var wire 1 D Cout $end
$var wire 1 E Sum $end
$upscope $end
$scope module F4 $end
$var wire 1 F A $end
$var wire 1 G B $end
$var wire 1 H Cin $end
$var wire 1 I Cout $end
$var wire 1 J Sum $end
$upscope $end
$scope module F5 $end
$var wire 1 K A $end
$var wire 1 L B $end
$var wire 1 M Cin $end
$var wire 1 N Cout $end
$var wire 1 O Sum $end
$upscope $end
$scope module F6 $end
$var wire 1 P A $end
$var wire 1 Q B $end
$var wire 1 R Cin $end
$var wire 1 S Cout $end
$var wire 1 T Sum $end
$upscope $end
$scope module F7 $end
$var wire 1 U A $end
$var wire 1 V B $end
$var wire 1 W Cin $end
$var wire 1 * Cout $end
$var wire 1 X Sum $end
$upscope $end
$upscope $end
$scope module ControlUnit $end
$var wire 1 $ areset $end
$var wire 1 % clk $end
$var wire 8 Y multiplier [7:0] $end
$var reg 4 Z counter [3:0] $end
$var reg 2 [ state [1:0] $end
$upscope $end
$upscope $end
$upscope $end
$enddefinitions $end
#0
$dumpvars
bx [
bx Z
bx Y
xX
xW
xV
xU
xT
xS
xR
xQ
xP
xO
xN
xM
xL
xK
xJ
xI
xH
xG
xF
xE
xD
xC
xB
xA
x@
x?
x>
x=
x<
x;
x:
x9
x8
x7
x6
x5
x4
x3
bx 2
bx 1
00
bx /
bx .
bx -
bx ,
bx +
x*
bx )
bx (
bx '
bx &
0%
x$
bx #
bx "
bx !
$end
#5
14
18
1=
1B
1G
1L
1Q
1V
b0 Z
b0 )
b0 [
1%
b1100100 #
b1100100 '
b11111111 "
b11111111 &
b11111111 /
1$
#10
0*
1X
0W
0S
1T
0R
0N
1O
0M
0I
1J
0H
0D
1E
0C
0?
1@
0>
0:
1;
09
b0 1
05
b11111111 (
b11111111 2
16
03
07
0<
0A
0F
0K
0P
0U
b0 .
b0 !
b0 ,
b1100100 +
b1100100 Y
b0 -
0$
1%
#15
b1 Z
b10 )
b10 [
1%
#20
b10 Z
b110010 +
b110010 Y
b10 -
1%
#25
b11 Z
b1 )
b1 [
b11001 +
b11001 Y
1%
#30
1*
0X
19
1>
1C
1H
1M
1R
1W
15
1:
1?
1D
1I
1N
b1111111 1
1S
06
1;
1@
1E
1J
1O
b1111110 (
b1111110 2
1T
13
17
1<
1A
1F
1K
1P
b1111111 .
b100 Z
b10 )
b10 [
b1100 +
b1100 Y
b111111110000000 !
b111111110000000 ,
b1 -
1%
#35
b111110 (
b111110 2
0T
0P
b111111 .
b101 Z
b110 +
b110 Y
b11111111000000 !
b11111111000000 ,
b10 -
1%
#40
b11110 (
b11110 2
0O
0K
b11111 .
b110 Z
b1 )
b1 [
b11 +
b11 Y
b1111111100000 !
b1111111100000 ,
1%
#45
0J
b10001110 (
b10001110 2
1X
0F
1U
b10001111 .
b111 Z
b1 +
b1 Y
b1000111101110000 !
b1000111101110000 ,
b1 -
1%
#50
0E
b11000110 (
b11000110 2
1T
0A
1P
b11000111 .
b1000 Z
b10 )
b10 [
b0 +
b0 Y
b1100011100111000 !
b1100011100111000 ,
1%
#55
0@
1O
b1100010 (
b1100010 2
0X
0<
1K
0U
b1100011 .
b11 )
b11 [
b110001110011100 !
b110001110011100 ,
b10 -
1%
#60
b11 -
1%
#65
1%
#70
0*
1X
0W
0S
0R
0N
0M
0I
1J
0H
0D
1E
0C
0?
1@
0>
0:
09
b0 1
05
16
1;
1O
b11111111 (
b11111111 2
1T
03
07
0K
0P
b0 .
b0 !
b0 ,
b11111111 +
b11111111 Y
b0 Z
b0 )
b0 [
b11111111 #
b11111111 '
1$
1%
#75
b1 Z
b1 )
b1 [
b0 -
0$
1%
#80
1*
0X
19
1>
1C
1H
1M
1R
1W
15
1:
1?
1D
1I
1N
b1111111 1
1S
06
1;
1@
1E
1J
1O
b1111110 (
b1111110 2
1T
13
17
1<
1A
1F
1K
1P
b1111111 .
b10 Z
b1111111 +
b1111111 Y
b111111110000000 !
b111111110000000 ,
b1 -
1%
#85
0T
b10111110 (
b10111110 2
1X
0P
1U
b10111111 .
b11 Z
b111111 +
b111111 Y
b1011111101000000 !
b1011111101000000 ,
1%
#90
0O
b11011110 (
b11011110 2
1T
0K
1P
b11011111 .
b100 Z
b11111 +
b11111 Y
b1101111100100000 !
b1101111100100000 ,
1%
#95
0J
b11101110 (
b11101110 2
1O
0F
1K
b11101111 .
b101 Z
b1111 +
b1111 Y
b1110111100010000 !
b1110111100010000 ,
1%
#100
0E
b11110110 (
b11110110 2
1J
0A
1F
b11110111 .
b110 Z
b111 +
b111 Y
b1111011100001000 !
b1111011100001000 ,
1%
#105
0@
b11111010 (
b11111010 2
1E
0<
1A
b11111011 .
b111 Z
b11 +
b11 Y
b1111101100000100 !
b1111101100000100 ,
1%
#110
0;
b11111100 (
b11111100 2
1@
07
1<
b11111101 .
b1000 Z
b1 +
b1 Y
b1111110100000010 !
b1111110100000010 ,
1%
#115
09
b1111110 1
05
16
b11111101 (
b11111101 2
0;
03
17
b11111110 .
b11 )
b11 [
b0 +
b0 Y
b1111111000000001 !
b1111111000000001 ,
1%
#120
b11 -
1%
#125
1%
#130
1%
#135
0C
0H
0M
0R
0W
0?
0D
0I
0N
0S
0*
0>
b0 1
0:
07
0<
0A
0F
0K
0P
0U
0;
0@
0E
0J
0O
0T
b1 (
b1 2
0X
b0 .
b0 !
b0 ,
b1 +
b1 Y
08
0=
0B
0G
0L
0Q
0V
b0 Z
b0 )
b0 [
b1 #
b1 '
b1 "
b1 &
b1 /
1$
1%
#140
b1 Z
b1 )
b1 [
b0 -
0$
1%
#145
b10 Z
b10 )
b10 [
b0 +
b0 Y
b10000000 !
b10000000 ,
b1 -
1%
#150
b11 Z
b1000000 !
b1000000 ,
b10 -
1%
#155
b100 Z
b100000 !
b100000 ,
1%
#160
b101 Z
b10000 !
b10000 ,
1%
#165
b110 Z
b1000 !
b1000 ,
1%
#170
b111 Z
b100 !
b100 ,
1%
#175
b1000 Z
b10 !
b10 ,
1%
#180
b11 )
b11 [
b1 !
b1 ,
1%
#185
b11 -
1%
